speechpy/__init__.py
speechpy/feature.py
speechpy/functions.py
speechpy/processing.py
speechpy-2.4.dist-info/DESCRIPTION.rst
speechpy-2.4.dist-info/METADATA
speechpy-2.4.dist-info/RECORD
speechpy-2.4.dist-info/WHEEL
speechpy-2.4.dist-info/metadata.json
speechpy-2.4.dist-info/top_level.txt
